rgsucher/README.MD
rgsucher/__init__.py
rgsucher/requirements.txt
rgsucher/thirdparty.json
rgsucher-0.11.dist-info/LICENSE.rst
rgsucher-0.11.dist-info/METADATA
rgsucher-0.11.dist-info/WHEEL
rgsucher-0.11.dist-info/top_level.txt
rgsucher-0.11.dist-info/RECORD
