Metadata-Version: 2.1
Name: rgsucher
Version: 0.11
Summary: ripgrep search
Home-page: https://github.com/hansalemaos/rgsucher
Author: Johannes Fischer
Author-email: aulasparticularesdealemaosp@gmail.com
License: MIT
Keywords: ripgrep,regex
Classifier: Development Status :: 4 - Beta
Classifier: Programming Language :: Python :: 3 :: Only
Classifier: Programming Language :: Python :: 3.10
Classifier: Topic :: Software Development :: Libraries :: Python Modules
Classifier: Topic :: Utilities
License-File: LICENSE.rst
Requires-Dist: ujson
